xm_slurm-0.3.0.dist-info/METADATA
xm_slurm-0.3.0.dist-info/WHEEL
xm_slurm/__init__.py
xm_slurm/api.py
xm_slurm/batching.py
xm_slurm/config.py
xm_slurm/console.py
xm_slurm/contrib/clusters/__init__.py
xm_slurm/contrib/clusters/drac.py
xm_slurm/executables.py
xm_slurm/execution.py
xm_slurm/executors.py
xm_slurm/experiment.py
xm_slurm/job_blocks.py
xm_slurm/packageables.py
xm_slurm/packaging/__init__.py
xm_slurm/packaging/docker/__init__.py
xm_slurm/packaging/docker/abc.py
xm_slurm/packaging/docker/cloud.py
xm_slurm/packaging/docker/local.py
xm_slurm/packaging/registry.py
xm_slurm/packaging/router.py
xm_slurm/packaging/utils.py
xm_slurm/resources.py
xm_slurm/status.py
xm_slurm/templates/docker/docker-bake.hcl.j2
xm_slurm/templates/docker/mamba.Dockerfile
xm_slurm/templates/docker/pdm.Dockerfile
xm_slurm/templates/docker/python.Dockerfile
xm_slurm/templates/slurm/fragments/monitor.bash.j2
xm_slurm/templates/slurm/fragments/proxy.bash.j2
xm_slurm/templates/slurm/job-array.bash.j2
xm_slurm/templates/slurm/job-group.bash.j2
xm_slurm/templates/slurm/job.bash.j2
xm_slurm/templates/slurm/runtimes/apptainer.bash.j2
xm_slurm/templates/slurm/runtimes/podman.bash.j2
xm_slurm/utils.py
xm_slurm-0.3.0.dist-info/RECORD
