Metadata-Version: 2.1
Name: xm-slurm
Version: 0.3.0
Summary: Slurm backend for XManager.
Author-Email: Jesse Farebrother <jfarebro@cs.mcgill.ca>
License: MIT
Requires-Python: >=3.10
Requires-Dist: xmanager>=0.4.0
Requires-Dist: asyncssh>=2.13.2
Requires-Dist: humanize>=4.8.0
Requires-Dist: jinja2>=3.1.2
Requires-Dist: toml>=0.10.2
Requires-Dist: rich>=13.5.2
Requires-Dist: immutabledict>=3.0.0
Requires-Dist: backoff>=2.2.1
Requires-Dist: pathspec>=0.11.2; extra == "gcp"
Requires-Dist: google-cloud-storage>=2.11.0; extra == "gcp"
Requires-Dist: google-cloud-build>=3.20.0; extra == "gcp"
Requires-Dist: google-cloud-logging>=3.8.0; extra == "gcp"
Requires-Dist: google-cloud-iam>=2.12.2; extra == "gcp"
Requires-Dist: google-cloud-kms>=2.19.2; extra == "gcp"
Requires-Dist: google-crc32c>=1.5.0; extra == "gcp"
Requires-Dist: pytest>=7.4.3; extra == "test"
Provides-Extra: gcp
Provides-Extra: test
